{
  "generatedAt": "2026-07-20T19:38:47.651524+00:00",
  "dataSource": "live-osint",
  "assets": [
    {
      "name": "USS Dwight D. Eisenhower",
      "type": "Carrier",
      "status": "Deployed - Red Sea",
      "pos": [
        15.891566764502238,
        41.519761339975354
      ],
      "osintConfirmed": false
    },
    {
      "name": "USS Abraham Lincoln",
      "type": "Carrier",
      "status": "Deployed - Arabian Sea",
      "pos": [
        20.752228742322988,
        59.96290843116387
      ],
      "osintConfirmed": false
    },
    {
      "name": "USS Gerald R. Ford",
      "type": "Carrier",
      "status": "Deployed - Red Sea",
      "pos": [
        15.733738581354526,
        42.36193148201498
      ],
      "osintConfirmed": true
    },
    {
      "name": "USS Theodore Roosevelt",
      "type": "Carrier",
      "status": "Deployed - Pacific",
      "pos": [
        15.20800746790575,
        115.276506569924
      ],
      "osintConfirmed": false
    },
    {
      "name": "USS Bataan",
      "type": "Amphibious",
      "status": "Deployed - Red Sea",
      "pos": [
        15.3690699731519,
        42.20282818034542
      ],
      "osintConfirmed": false
    },
    {
      "name": "USS Boxer",
      "type": "Amphibious",
      "status": "Deployed - Pacific",
      "pos": [
        14.52742164930862,
        115.06700964718151
      ],
      "osintConfirmed": false
    },
    {
      "name": "USS Carney",
      "type": "Destroyer",
      "status": "Deployed - Red Sea",
      "pos": [
        15.037853399979287,
        41.55272043512208
      ],
      "osintConfirmed": false
    },
    {
      "name": "USS Mason",
      "type": "Destroyer",
      "status": "Deployed - Red Sea",
      "pos": [
        15.588840049137701,
        42.06255004249668
      ],
      "osintConfirmed": false
    },
    {
      "name": "USS Laboon",
      "type": "Destroyer",
      "status": "Deployed - Red Sea",
      "pos": [
        15.723869786808612,
        41.500842752580375
      ],
      "osintConfirmed": false
    },
    {
      "name": "USS Florida",
      "type": "Submarine",
      "status": "Deployed - Persian Gulf",
      "pos": [
        25.83582672732873,
        52.026392056743205
      ],
      "osintConfirmed": false
    }
  ],
  "articlesAnalyzed": 52
}