{
  "generatedAt": "2026-06-21T19:24:09.313162+00:00",
  "dataSource": "live-osint",
  "assets": [
    {
      "name": "USS Dwight D. Eisenhower",
      "type": "Carrier",
      "status": "Deployed - Red Sea",
      "pos": [
        15.68840155962458,
        41.54801931416204
      ],
      "osintConfirmed": false
    },
    {
      "name": "USS Abraham Lincoln",
      "type": "Carrier",
      "status": "Deployed - Arabian Sea",
      "pos": [
        20.544148896514102,
        59.55332879496984
      ],
      "osintConfirmed": false
    },
    {
      "name": "USS Gerald R. Ford",
      "type": "Carrier",
      "status": "Deployed - Mediterranean",
      "pos": [
        33.70839299873171,
        30.293124899541304
      ],
      "osintConfirmed": false
    },
    {
      "name": "USS Theodore Roosevelt",
      "type": "Carrier",
      "status": "Deployed - Pacific",
      "pos": [
        14.703392951351763,
        115.21745857581396
      ],
      "osintConfirmed": false
    },
    {
      "name": "USS Bataan",
      "type": "Amphibious",
      "status": "Deployed - Red Sea",
      "pos": [
        15.77836428933287,
        41.64362422658487
      ],
      "osintConfirmed": false
    },
    {
      "name": "USS Boxer",
      "type": "Amphibious",
      "status": "Deployed - Pacific",
      "pos": [
        14.911406661320406,
        115.48146384939284
      ],
      "osintConfirmed": false
    },
    {
      "name": "USS Carney",
      "type": "Destroyer",
      "status": "Deployed - Red Sea",
      "pos": [
        15.121638679526086,
        41.55310896586066
      ],
      "osintConfirmed": false
    },
    {
      "name": "USS Mason",
      "type": "Destroyer",
      "status": "Deployed - Red Sea",
      "pos": [
        15.013494047834282,
        42.10604349038552
      ],
      "osintConfirmed": false
    },
    {
      "name": "USS Laboon",
      "type": "Destroyer",
      "status": "Deployed - Red Sea",
      "pos": [
        15.3546968545232,
        41.880080835405316
      ],
      "osintConfirmed": false
    },
    {
      "name": "USS Florida",
      "type": "Submarine",
      "status": "Deployed - Persian Gulf",
      "pos": [
        25.771714326730102,
        51.609406849694004
      ],
      "osintConfirmed": false
    }
  ],
  "articlesAnalyzed": 54
}