{
  "generatedAt": "2026-06-17T03:35:25.919739+00:00",
  "dataSource": "live-osint",
  "assets": [
    {
      "name": "USS Dwight D. Eisenhower",
      "type": "Carrier",
      "status": "Deployed - Red Sea",
      "pos": [
        15.078537306948249,
        41.9438021058967
      ],
      "osintConfirmed": false
    },
    {
      "name": "USS Abraham Lincoln",
      "type": "Carrier",
      "status": "Deployed - Arabian Sea",
      "pos": [
        21.418995719790434,
        59.52216368666235
      ],
      "osintConfirmed": false
    },
    {
      "name": "USS Gerald R. Ford",
      "type": "Carrier",
      "status": "Deployed - Mediterranean",
      "pos": [
        34.09851722063125,
        29.991199566460324
      ],
      "osintConfirmed": false
    },
    {
      "name": "USS Theodore Roosevelt",
      "type": "Carrier",
      "status": "Deployed - Pacific",
      "pos": [
        14.627499253117275,
        114.93166116985607
      ],
      "osintConfirmed": true
    },
    {
      "name": "USS Bataan",
      "type": "Amphibious",
      "status": "Deployed - Red Sea",
      "pos": [
        15.993531450508375,
        41.761189195010665
      ],
      "osintConfirmed": false
    },
    {
      "name": "USS Boxer",
      "type": "Amphibious",
      "status": "Deployed - Pacific",
      "pos": [
        15.183753868433532,
        115.11683098461702
      ],
      "osintConfirmed": false
    },
    {
      "name": "USS Carney",
      "type": "Destroyer",
      "status": "Deployed - Red Sea",
      "pos": [
        15.202352376124665,
        42.42545259410232
      ],
      "osintConfirmed": false
    },
    {
      "name": "USS Mason",
      "type": "Destroyer",
      "status": "Deployed - Red Sea",
      "pos": [
        15.006502820524096,
        41.712907144761466
      ],
      "osintConfirmed": false
    },
    {
      "name": "USS Laboon",
      "type": "Destroyer",
      "status": "Deployed - Red Sea",
      "pos": [
        15.67022173809489,
        42.10739988090678
      ],
      "osintConfirmed": false
    },
    {
      "name": "USS Florida",
      "type": "Submarine",
      "status": "Deployed - Persian Gulf",
      "pos": [
        25.754528423666752,
        52.154780591553596
      ],
      "osintConfirmed": false
    }
  ],
  "articlesAnalyzed": 54
}