{
  "us": {
    "positive": 42,
    "negative": 51,
    "neutral": 7,
    "wordCloud": [
      {
        "word": "trump",
        "count": 65,
        "sentiment": "neutral"
      },
      {
        "word": "platner",
        "count": 30,
        "sentiment": "neutral"
      },
      {
        "word": "senate",
        "count": 24,
        "sentiment": "neutral"
      },
      {
        "word": "democrats",
        "count": 18,
        "sentiment": "neutral"
      },
      {
        "word": "nato",
        "count": 17,
        "sentiment": "neutral"
      },
      {
        "word": "graham",
        "count": 15,
        "sentiment": "neutral"
      },
      {
        "word": "race",
        "count": 15,
        "sentiment": "neutral"
      },
      {
        "word": "fifa",
        "count": 15,
        "sentiment": "neutral"
      },
      {
        "word": "red",
        "count": 14,
        "sentiment": "neutral"
      },
      {
        "word": "assault",
        "count": 14,
        "sentiment": "negative"
      },
      {
        "word": "balogun",
        "count": 12,
        "sentiment": "neutral"
      },
      {
        "word": "calls",
        "count": 11,
        "sentiment": "neutral"
      },
      {
        "word": "maine",
        "count": 11,
        "sentiment": "neutral"
      },
      {
        "word": "cup",
        "count": 11,
        "sentiment": "neutral"
      },
      {
        "word": "accounts",
        "count": 11,
        "sentiment": "neutral"
      },
      {
        "word": "macron",
        "count": 10,
        "sentiment": "neutral"
      },
      {
        "word": "sexual",
        "count": 10,
        "sentiment": "neutral"
      },
      {
        "word": "vance",
        "count": 10,
        "sentiment": "neutral"
      },
      {
        "word": "damascus",
        "count": 9,
        "sentiment": "neutral"
      },
      {
        "word": "visit",
        "count": 9,
        "sentiment": "neutral"
      },
      {
        "word": "summit",
        "count": 9,
        "sentiment": "neutral"
      },
      {
        "word": "card",
        "count": 9,
        "sentiment": "neutral"
      },
      {
        "word": "politics",
        "count": 8,
        "sentiment": "neutral"
      },
      {
        "word": "president",
        "count": 8,
        "sentiment": "neutral"
      },
      {
        "word": "candidate",
        "count": 8,
        "sentiment": "neutral"
      },
      {
        "word": "white",
        "count": 8,
        "sentiment": "neutral"
      },
      {
        "word": "house",
        "count": 8,
        "sentiment": "neutral"
      },
      {
        "word": "explosions",
        "count": 7,
        "sentiment": "neutral"
      },
      {
        "word": "drop",
        "count": 7,
        "sentiment": "negative"
      },
      {
        "word": "accused",
        "count": 7,
        "sentiment": "negative"
      }
    ],
    "totalPersonalities": 384,
    "generatedAt": "2026-07-07T11:43:03.810982+00:00",
    "nextRefresh": "2026-07-07T11:43:03.810982+00:00",
    "articlesAnalyzed": 342,
    "matchedMentions": 190,
    "uniquePersonalities": 47,
    "dataSource": "live-rss"
  },
  "india": {
    "positive": 53,
    "negative": 28,
    "neutral": 19,
    "wordCloud": [
      {
        "word": "modi",
        "count": 13,
        "sentiment": "neutral"
      },
      {
        "word": "indonesia",
        "count": 11,
        "sentiment": "neutral"
      },
      {
        "word": "siya",
        "count": 7,
        "sentiment": "neutral"
      },
      {
        "word": "ketan",
        "count": 7,
        "sentiment": "neutral"
      },
      {
        "word": "married",
        "count": 6,
        "sentiment": "neutral"
      },
      {
        "word": "months",
        "count": 6,
        "sentiment": "neutral"
      },
      {
        "word": "india",
        "count": 5,
        "sentiment": "neutral"
      },
      {
        "word": "lover",
        "count": 4,
        "sentiment": "positive"
      },
      {
        "word": "engagement",
        "count": 4,
        "sentiment": "positive"
      },
      {
        "word": "target",
        "count": 4,
        "sentiment": "neutral"
      },
      {
        "word": "lucknow",
        "count": 3,
        "sentiment": "neutral"
      },
      {
        "word": "chetan",
        "count": 3,
        "sentiment": "neutral"
      },
      {
        "word": "highest",
        "count": 3,
        "sentiment": "neutral"
      },
      {
        "word": "honour",
        "count": 3,
        "sentiment": "positive"
      },
      {
        "word": "president",
        "count": 3,
        "sentiment": "neutral"
      },
      {
        "word": "calls",
        "count": 3,
        "sentiment": "neutral"
      },
      {
        "word": "killing",
        "count": 3,
        "sentiment": "negative"
      },
      {
        "word": "secretly",
        "count": 3,
        "sentiment": "neutral"
      },
      {
        "word": "kohli",
        "count": 3,
        "sentiment": "neutral"
      },
      {
        "word": "sparked",
        "count": 3,
        "sentiment": "neutral"
      },
      {
        "word": "bajaj",
        "count": 3,
        "sentiment": "neutral"
      },
      {
        "word": "emkay",
        "count": 3,
        "sentiment": "neutral"
      },
      {
        "word": "global",
        "count": 3,
        "sentiment": "neutral"
      },
      {
        "word": "financial",
        "count": 3,
        "sentiment": "neutral"
      },
      {
        "word": "rape",
        "count": 2,
        "sentiment": "negative"
      },
      {
        "word": "torture",
        "count": 2,
        "sentiment": "negative"
      },
      {
        "word": "dowry",
        "count": 2,
        "sentiment": "neutral"
      },
      {
        "word": "horror",
        "count": 2,
        "sentiment": "negative"
      },
      {
        "word": "year-old",
        "count": 2,
        "sentiment": "neutral"
      },
      {
        "word": "railway",
        "count": 2,
        "sentiment": "neutral"
      }
    ],
    "totalPersonalities": 295,
    "generatedAt": "2026-07-07T11:43:17.861669+00:00",
    "nextRefresh": "2026-07-07T11:43:17.861669+00:00",
    "articlesAnalyzed": 482,
    "matchedMentions": 68,
    "uniquePersonalities": 34,
    "dataSource": "live-rss"
  }
}