{
  "us": {
    "positive": 58,
    "negative": 35,
    "neutral": 7,
    "wordCloud": [
      {
        "word": "trump",
        "count": 59,
        "sentiment": "neutral"
      },
      {
        "word": "wedding",
        "count": 19,
        "sentiment": "neutral"
      },
      {
        "word": "swift",
        "count": 15,
        "sentiment": "positive"
      },
      {
        "word": "reflecting",
        "count": 10,
        "sentiment": "neutral"
      },
      {
        "word": "pool",
        "count": 10,
        "sentiment": "neutral"
      },
      {
        "word": "taylor",
        "count": 9,
        "sentiment": "neutral"
      },
      {
        "word": "court",
        "count": 8,
        "sentiment": "neutral"
      },
      {
        "word": "kelce",
        "count": 8,
        "sentiment": "neutral"
      },
      {
        "word": "national",
        "count": 8,
        "sentiment": "neutral"
      },
      {
        "word": "olympian",
        "count": 7,
        "sentiment": "neutral"
      },
      {
        "word": "latest",
        "count": 7,
        "sentiment": "neutral"
      },
      {
        "word": "madison",
        "count": 6,
        "sentiment": "neutral"
      },
      {
        "word": "square",
        "count": 6,
        "sentiment": "neutral"
      },
      {
        "word": "garden",
        "count": 6,
        "sentiment": "neutral"
      },
      {
        "word": "ahead",
        "count": 6,
        "sentiment": "neutral"
      },
      {
        "word": "former",
        "count": 6,
        "sentiment": "neutral"
      },
      {
        "word": "president",
        "count": 6,
        "sentiment": "neutral"
      },
      {
        "word": "america",
        "count": 6,
        "sentiment": "neutral"
      },
      {
        "word": "administration",
        "count": 6,
        "sentiment": "neutral"
      },
      {
        "word": "indicted",
        "count": 5,
        "sentiment": "neutral"
      },
      {
        "word": "travis",
        "count": 5,
        "sentiment": "neutral"
      },
      {
        "word": "power",
        "count": 5,
        "sentiment": "neutral"
      },
      {
        "word": "ban",
        "count": 5,
        "sentiment": "negative"
      },
      {
        "word": "voting",
        "count": 5,
        "sentiment": "neutral"
      },
      {
        "word": "air",
        "count": 5,
        "sentiment": "neutral"
      },
      {
        "word": "biden",
        "count": 5,
        "sentiment": "neutral"
      },
      {
        "word": "abuzz",
        "count": 4,
        "sentiment": "neutral"
      },
      {
        "word": "eager",
        "count": 4,
        "sentiment": "positive"
      },
      {
        "word": "swifties",
        "count": 4,
        "sentiment": "neutral"
      },
      {
        "word": "swift-kelce",
        "count": 4,
        "sentiment": "neutral"
      }
    ],
    "totalPersonalities": 384,
    "generatedAt": "2026-07-02T20:59:27.731200+00:00",
    "nextRefresh": "2026-07-02T20:59:27.731200+00:00",
    "articlesAnalyzed": 347,
    "matchedMentions": 159,
    "uniquePersonalities": 48,
    "dataSource": "live-rss"
  },
  "india": {
    "positive": 33,
    "negative": 37,
    "neutral": 30,
    "wordCloud": [
      {
        "word": "modi",
        "count": 8,
        "sentiment": "neutral"
      },
      {
        "word": "tmc",
        "count": 7,
        "sentiment": "neutral"
      },
      {
        "word": "minister",
        "count": 6,
        "sentiment": "neutral"
      },
      {
        "word": "puri",
        "count": 6,
        "sentiment": "neutral"
      },
      {
        "word": "india",
        "count": 6,
        "sentiment": "neutral"
      },
      {
        "word": "defence",
        "count": 5,
        "sentiment": "positive"
      },
      {
        "word": "hardeep",
        "count": 5,
        "sentiment": "neutral"
      },
      {
        "word": "khan",
        "count": 5,
        "sentiment": "neutral"
      },
      {
        "word": "takaichi",
        "count": 5,
        "sentiment": "neutral"
      },
      {
        "word": "oil",
        "count": 4,
        "sentiment": "neutral"
      },
      {
        "word": "abdullah",
        "count": 4,
        "sentiment": "neutral"
      },
      {
        "word": "dialogue",
        "count": 4,
        "sentiment": "neutral"
      },
      {
        "word": "japan",
        "count": 4,
        "sentiment": "neutral"
      },
      {
        "word": "seeks",
        "count": 4,
        "sentiment": "neutral"
      },
      {
        "word": "claims",
        "count": 4,
        "sentiment": "neutral"
      },
      {
        "word": "prices",
        "count": 4,
        "sentiment": "neutral"
      },
      {
        "word": "calls",
        "count": 3,
        "sentiment": "neutral"
      },
      {
        "word": "singh",
        "count": 3,
        "sentiment": "neutral"
      },
      {
        "word": "surrender",
        "count": 3,
        "sentiment": "neutral"
      },
      {
        "word": "court",
        "count": 3,
        "sentiment": "neutral"
      },
      {
        "word": "house",
        "count": 3,
        "sentiment": "neutral"
      },
      {
        "word": "firing",
        "count": 3,
        "sentiment": "negative"
      },
      {
        "word": "ties",
        "count": 3,
        "sentiment": "neutral"
      },
      {
        "word": "soon",
        "count": 3,
        "sentiment": "neutral"
      },
      {
        "word": "backs",
        "count": 3,
        "sentiment": "negative"
      },
      {
        "word": "pakistan",
        "count": 3,
        "sentiment": "neutral"
      },
      {
        "word": "real",
        "count": 3,
        "sentiment": "neutral"
      },
      {
        "word": "sanae",
        "count": 3,
        "sentiment": "neutral"
      },
      {
        "word": "chopra",
        "count": 3,
        "sentiment": "neutral"
      },
      {
        "word": "gender",
        "count": 3,
        "sentiment": "neutral"
      }
    ],
    "totalPersonalities": 295,
    "generatedAt": "2026-07-02T20:59:35.633580+00:00",
    "nextRefresh": "2026-07-02T20:59:35.633580+00:00",
    "articlesAnalyzed": 466,
    "matchedMentions": 70,
    "uniquePersonalities": 40,
    "dataSource": "live-rss"
  }
}